README.txt
setup.cfg
setup.py
docs/CREDITS.txt
docs/HISTORY.txt
docs/INSTALL.txt
docs/LICENSE.GPL
docs/LICENSE.txt
getpaid/__init__.py
getpaid.luottokunta.egg-info/PKG-INFO
getpaid.luottokunta.egg-info/SOURCES.txt
getpaid.luottokunta.egg-info/dependency_links.txt
getpaid.luottokunta.egg-info/entry_points.txt
getpaid.luottokunta.egg-info/namespace_packages.txt
getpaid.luottokunta.egg-info/not-zip-safe
getpaid.luottokunta.egg-info/paster_plugins.txt
getpaid.luottokunta.egg-info/requires.txt
getpaid.luottokunta.egg-info/top_level.txt
getpaid/luottokunta/README.txt
getpaid/luottokunta/__init__.py
getpaid/luottokunta/config.py
getpaid/luottokunta/configure.zcml
getpaid/luottokunta/i18n.sh
getpaid/luottokunta/interfaces.py
getpaid/luottokunta/luottokunta.py
getpaid/luottokunta/options.py
getpaid/luottokunta/overrides.zcml
getpaid/luottokunta/paymentprocessors.zcml
getpaid/luottokunta/version.txt
getpaid/luottokunta/adapters/__init__.py
getpaid/luottokunta/adapters/configure.zcml
getpaid/luottokunta/adapters/order.py
getpaid/luottokunta/browser/__init__.py
getpaid/luottokunta/browser/admin.py
getpaid/luottokunta/browser/button.py
getpaid/luottokunta/browser/checkout.py
getpaid/luottokunta/browser/configure.zcml
getpaid/luottokunta/browser/overrides.zcml
getpaid/luottokunta/browser/templates/button.pt
getpaid/luottokunta/browser/templates/checkout-cancelled-declined.pt
getpaid/luottokunta/browser/templates/checkout-cancelled.pt
getpaid/luottokunta/browser/templates/checkout-declined.pt
getpaid/luottokunta/browser/templates/checkout-luottokunta-pay.pt
getpaid/luottokunta/browser/templates/checkout-thank-you.pt
getpaid/luottokunta/browser/viewlets/__init__.py
getpaid/luottokunta/browser/viewlets/configure.zcml
getpaid/luottokunta/browser/viewlets/interfaces.py
getpaid/luottokunta/locales/empty.pt
getpaid/luottokunta/locales/getpaid.luottokunta.pot
getpaid/luottokunta/locales/manual.pot
getpaid/luottokunta/locales/fi/LC_MESSAGES/getpaid.luottokunta.mo
getpaid/luottokunta/locales/fi/LC_MESSAGES/getpaid.luottokunta.po
getpaid/luottokunta/locales/ja/LC_MESSAGES/getpaid.luottokunta.po
getpaid/luottokunta/tests/__init__.py
getpaid/luottokunta/tests/test_doctests.py
getpaid/luottokunta/tests/unittests/adapters_unittests.txt
getpaid/luottokunta/tests/unittests/utilities_unittests.txt
getpaid/luottokunta/utilities/__init__.py
getpaid/luottokunta/utilities/configure.zcml
