Metadata-Version: 1.0
Name: getpaid.luottokunta
Version: 0.4.0
Summary: Luottokunta payment processor for getpaid.
Home-page: http://pypi.python.org/pypi/getpaid.luottokunta
Author: Taito Horiuchi
Author-email: taito.horiuchi@gmail.com
License: GPL
Platform: UNKNOWN
Classifier: Framework :: Plone
Classifier: Programming Language :: Python
Classifier: Topic :: Software Development :: Libraries :: Python Modules
